interro/__init__.py
interro/cli.py
interro/config.py
interro/formatter.py
interro/indexer.py
interro/llm_agent.py
interro/main.py
interro/retriever.py
tests/__init__.py
interro-0.1.3.dist-info/METADATA
interro-0.1.3.dist-info/WHEEL
interro-0.1.3.dist-info/entry_points.txt
interro-0.1.3.dist-info/top_level.txt
interro-0.1.3.dist-info/RECORD
